chemometricspy/__init__.py
chemometricspy/doe/__init__.py
chemometricspy/doe/bbd.py
chemometricspy/doe/ccd.py
chemometricspy/doe/efeitos.py
chemometricspy/doe/factorial.py
chemometricspy/doe/fractional_factorial.py
chemometricspy/doe/regression.py
chemometricspy-0.1.2.dist-info/licenses/LICENSE
chemometricspy-0.1.2.dist-info/METADATA
chemometricspy-0.1.2.dist-info/WHEEL
chemometricspy-0.1.2.dist-info/top_level.txt
chemometricspy-0.1.2.dist-info/RECORD
