Metadata-Version: 2.4
Name: chemometricspy
Version: 0.1.2
Summary: *ChemometricsPy: A scientific Python library for chemometric modeling*.
Author: Leonardo Guimarães
Author-email: Leonardo Guimarães <leo.sguimaraes4@gmail.com>
License: MIT
Project-URL: Homepage, https://github.com/leosguimaraes/chemometricspy
Project-URL: Source, https://github.com/leosguimaraes/chemometricspy
Requires-Python: >=3.8
License-File: LICENSE
Requires-Dist: numpy
Requires-Dist: pandas
Requires-Dist: matplotlib
Dynamic: author
Dynamic: license-file
